certbot_dns_gandi/__init__.py
certbot_dns_gandi/gandi_api.py
certbot_dns_gandi/main.py
certbot_dns_gandi-1.6.1.dist-info/METADATA
certbot_dns_gandi-1.6.1.dist-info/WHEEL
certbot_dns_gandi-1.6.1.dist-info/entry_points.txt
certbot_dns_gandi-1.6.1.dist-info/licenses/LICENSE
certbot_dns_gandi-1.6.1.dist-info/RECORD
